harlequin/VERSION
harlequin/__init__.py
harlequin/harlequin.py
harlequin/repo.py
harlequin_dataset-1.0.0.dist-info/METADATA
harlequin_dataset-1.0.0.dist-info/WHEEL
harlequin_dataset-1.0.0.dist-info/RECORD
