Metadata-Version: 2.1
Name: harlequin-dataset
Version: 1.0.0
Summary: Harlequin: Color-driven Generation of Synthetic Data for Referring Expression Comprehension
License: MIT
Author: lparolari
Author-email: luca.parolari23@gmail.com
Requires-Python: >=3.10,<4.0
Classifier: License :: OSI Approved :: MIT License
Classifier: Programming Language :: Python :: 3
Classifier: Programming Language :: Python :: 3.10
Classifier: Programming Language :: Python :: 3.11
Classifier: Programming Language :: Python :: 3.12
